jumpssh/__init__.py
jumpssh/__version__.py
jumpssh/exception.py
jumpssh/restclient.py
jumpssh/session.py
jumpssh/util.py
jumpssh-1.6.5.dist-info/METADATA
jumpssh-1.6.5.dist-info/RECORD
jumpssh-1.6.5.dist-info/WHEEL
jumpssh-1.6.5.dist-info/top_level.txt
lib/jumpssh/__init__.py
lib/jumpssh/__version__.py
lib/jumpssh/exception.py
lib/jumpssh/restclient.py
lib/jumpssh/session.py
lib/jumpssh/util.py
